astrodbkit/__init__.py
astrodbkit/astrodb.py
astrodbkit/schema_example.py
astrodbkit/schema_example_felis.yaml
astrodbkit/spectra.py
astrodbkit/utils.py
astrodbkit/version.py
astrodbkit/views.py
astrodbkit/tests/__init__.py
astrodbkit/tests/test_astrodb.py
astrodbkit/tests/test_spectra.py
astrodbkit/tests/test_utils.py
astrodbkit/tests/test_views.py
astrodbkit-2.5.dist-info/METADATA
astrodbkit-2.5.dist-info/WHEEL
astrodbkit-2.5.dist-info/top_level.txt
astrodbkit-2.5.dist-info/RECORD
