Metadata-Version: 2.1
Name: astrodbkit
Version: 2.5
Summary: Astronomical database handler code
Author: David Rodriguez
Author-email: David Rodriguez <drodriguez@stsci.edu>
License: BSD 3-Clause
Project-URL: Repository, https://github.com/astrodbtoolkit/AstrodbKit
Requires-Python: >=3.11
Requires-Dist: astropy>7.0
Requires-Dist: astroquery>=0.4.9
Requires-Dist: sqlalchemy>=2.0.38
Requires-Dist: pandas>=1.0.4
Requires-Dist: packaging
Requires-Dist: specutils>=2.0
Requires-Dist: tqdm
Provides-Extra: all
Requires-Dist: astrodbkit[docs,felis,test]; extra == "all"
Provides-Extra: docs
Requires-Dist: sphinx-astropy; extra == "docs"
Provides-Extra: felis
Requires-Dist: lsst-felis; extra == "felis"
Provides-Extra: test
Requires-Dist: pytest; extra == "test"
Requires-Dist: pytest-cov; extra == "test"
Requires-Dist: pytest-astropy; extra == "test"
Requires-Dist: darker>=1.7.2; extra == "test"
Requires-Dist: black>=23.9.1; extra == "test"
Requires-Dist: pre-commit>=3.4.0; extra == "test"
Requires-Dist: ruff>=0.3.7; extra == "test"
